{
  "timestamp": "2025-12-02T12:31:32.334Z",
  "total": 45,
  "success": 45,
  "failed": 0,
  "successRate": "100.0%",
  "entries": [
    {
      "slug": "ancient-sandals",
      "title": "Ancient Greek Running Sandals",
      "success": true,
      "chosenSource": "Wikipedia",
      "chosenUrl": "https://upload.wikimedia.org/wikipedia/commons/e/e9/Sandals_on_feet.jpg",
      "license": "CC BY-SA or Public Domain",
      "author": "",
      "localPath": "objects/images/ancient-sandals.jpg",
      "notes": "artifact-photo"
    },
    {
      "slug": "greek-discus",
      "title": "Ancient Greek Discus",
      "success": true,
      "chosenSource": "Wikipedia",
      "chosenUrl": "https://upload.wikimedia.org/wikipedia/commons/b/b4/Robert_Harting_%282008%29.jpg",
      "license": "CC BY-SA or Public Domain",
      "author": "",
      "localPath": "objects/images/greek-discus.jpg",
      "notes": "artifact-photo"
    },
    {
      "slug": "roman-training-gear",
      "title": "Roman Gladiator Training Weights",
      "success": true,
      "chosenSource": "Wikipedia",
      "chosenUrl": "https://upload.wikimedia.org/wikipedia/commons/0/07/Astyanax_vs_Kalendio_mosaic.jpg",
      "license": "CC BY-SA or Public Domain",
      "author": "",
      "localPath": "objects/images/roman-training-gear.jpg",
      "notes": "artifact-photo"
    },
    {
      "slug": "olympic-torch",
      "title": "1936 Berlin Olympic Torch",
      "success": true,
      "chosenSource": "Wikipedia",
      "chosenUrl": "https://upload.wikimedia.org/wikipedia/commons/5/5c/Olympic_rings_without_rims.svg",
      "license": "CC BY-SA or Public Domain",
      "author": "",
      "localPath": "objects/images/olympic-torch.jpg",
      "notes": "artifact-photo"
    },
    {
      "slug": "olympic-medal-1924",
      "title": "1924 Paris Olympic Gold Medal",
      "success": true,
      "chosenSource": "Wikipedia",
      "chosenUrl": "https://upload.wikimedia.org/wikipedia/commons/4/45/1924_Summer_Olympics_logo.svg",
      "license": "CC BY-SA or Public Domain",
      "author": "",
      "localPath": "objects/images/olympic-medal-1924.jpg",
      "notes": "artifact-photo"
    },
    {
      "slug": "first-olympic-program",
      "title": "1896 Athens Olympic Program",
      "success": true,
      "chosenSource": "Wikipedia",
      "chosenUrl": "https://upload.wikimedia.org/wikipedia/commons/a/ae/Commemorative_album_of_1896_Olympic_Games_-_cover_by_E._Gilli%C3%A9ron.jpg",
      "license": "CC BY-SA or Public Domain",
      "author": "",
      "localPath": "objects/images/first-olympic-program.jpg",
      "notes": "artifact-photo"
    },
    {
      "slug": "first-stopwatch",
      "title": "Heuer Stopwatch, 1916",
      "success": true,
      "chosenSource": "Wikipedia",
      "chosenUrl": "https://upload.wikimedia.org/wikipedia/commons/d/de/TAG_Heuer_Logo.svg",
      "license": "CC BY-SA or Public Domain",
      "author": "",
      "localPath": "objects/images/first-stopwatch.jpg",
      "notes": "artifact-photo"
    },
    {
      "slug": "mechanical-chronograph",
      "title": "Omega Chronograph, 1932",
      "success": true,
      "chosenSource": "Wikipedia",
      "chosenUrl": "https://upload.wikimedia.org/wikipedia/commons/c/cd/Vintage_Omega_Speedmaster_%22Pre-moon%22.jpg",
      "license": "CC BY-SA or Public Domain",
      "author": "",
      "localPath": "objects/images/mechanical-chronograph.jpg",
      "notes": "artifact-photo"
    },
    {
      "slug": "electronic-timer",
      "title": "Electronic Timing System, 1968",
      "success": true,
      "chosenSource": "Wikipedia",
      "chosenUrl": "https://upload.wikimedia.org/wikipedia/commons/9/9d/PanAmRioTiming.jpg",
      "license": "CC BY-SA or Public Domain",
      "author": "",
      "localPath": "objects/images/electronic-timer.jpg",
      "notes": "artifact-photo"
    },
    {
      "slug": "vintage-sneakers",
      "title": "Converse All-Stars, 1923",
      "success": true,
      "chosenSource": "Wikipedia",
      "chosenUrl": "https://upload.wikimedia.org/wikipedia/commons/a/a5/Black_Converse_sneakers.JPG",
      "license": "CC BY-SA or Public Domain",
      "author": "",
      "localPath": "objects/images/vintage-sneakers.jpg",
      "notes": "artifact-photo"
    },
    {
      "slug": "early-running-shoe",
      "title": "Adidas Marathon Running Shoe, 1950s",
      "success": true,
      "chosenSource": "Wikipedia",
      "chosenUrl": "https://upload.wikimedia.org/wikipedia/en/8/87/Onitsuka_Tiger_Logo.svg",
      "license": "CC BY-SA or Public Domain",
      "author": "",
      "localPath": "objects/images/early-running-shoe.jpg",
      "notes": "artifact-photo"
    },
    {
      "slug": "track-spike-evolution",
      "title": "Track Spike Collection, 1960s-1980s",
      "success": true,
      "chosenSource": "Wikipedia",
      "chosenUrl": "https://upload.wikimedia.org/wikipedia/commons/f/fd/Jackee88.jpg",
      "license": "CC BY-SA or Public Domain",
      "author": "",
      "localPath": "objects/images/track-spike-evolution.jpg",
      "notes": "artifact-photo"
    },
    {
      "slug": "first-record-book",
      "title": "IAAF World Records Book, 1912",
      "success": true,
      "chosenSource": "Wikipedia",
      "chosenUrl": "https://upload.wikimedia.org/wikipedia/commons/6/62/World_record_progression_100m_men.svg",
      "license": "CC BY-SA or Public Domain",
      "author": "",
      "localPath": "objects/images/first-record-book.jpg",
      "notes": "artifact-photo"
    },
    {
      "slug": "olympic-records-archive",
      "title": "Olympic Records Archive, 1896-1950",
      "success": true,
      "chosenSource": "Wikipedia",
      "chosenUrl": "https://upload.wikimedia.org/wikipedia/commons/1/15/Kelvin_Kiptum_2023_Chicago_Marathon.jpg",
      "license": "CC BY-SA or Public Domain",
      "author": "",
      "localPath": "objects/images/olympic-records-archive.jpg",
      "notes": "artifact-photo"
    },
    {
      "slug": "world-records-timeline",
      "title": "World Records Timeline Display, 1912-2020",
      "success": true,
      "chosenSource": "Wikipedia",
      "chosenUrl": "https://upload.wikimedia.org/wikipedia/commons/d/d4/John_Isner_at_the_2009_US_Open_01.jpg",
      "license": "CC BY-SA or Public Domain",
      "author": "",
      "localPath": "objects/images/world-records-timeline.jpg",
      "notes": "artifact-photo"
    },
    {
      "slug": "mesoamerican-ball",
      "title": "Mesoamerican Rubber Ball",
      "success": true,
      "chosenSource": "Wikipedia",
      "chosenUrl": "https://upload.wikimedia.org/wikipedia/commons/5/59/Mesoamerica_-_manopla_and_ball.jpg",
      "license": "CC BY-SA or Public Domain",
      "author": "",
      "localPath": "objects/images/mesoamerican-ball.jpg",
      "notes": "artifact-photo"
    },
    {
      "slug": "sumo-training-gear",
      "title": "Traditional Sumo Training Equipment",
      "success": true,
      "chosenSource": "Wikipedia",
      "chosenUrl": "https://upload.wikimedia.org/wikipedia/commons/2/2a/%E8%A6%AA%E6%96%B9%E3%80%81%E5%BC%9F%E5%AD%90%E3%81%AE%E9%9B%86%E5%90%88%E5%86%99%E7%9C%9F.jpg",
      "license": "CC BY-SA or Public Domain",
      "author": "",
      "localPath": "objects/images/sumo-training-gear.jpg",
      "notes": "artifact-photo"
    },
    {
      "slug": "african-running-tradition",
      "title": "East African Running Tradition Artifacts",
      "success": true,
      "chosenSource": "Wikipedia",
      "chosenUrl": "https://upload.wikimedia.org/wikipedia/commons/a/ad/Kalambo_Falls.jpg",
      "license": "CC BY-SA or Public Domain",
      "author": "",
      "localPath": "objects/images/african-running-tradition.jpg",
      "notes": "artifact-photo"
    },
    {
      "slug": "motion-capture-rig",
      "title": "Vicon Motion Capture System, 2010",
      "success": true,
      "chosenSource": "Wikipedia",
      "chosenUrl": "https://upload.wikimedia.org/wikipedia/commons/9/93/Alvernia_Studios_1.jpg",
      "license": "CC BY-SA or Public Domain",
      "author": "",
      "localPath": "objects/images/motion-capture-rig.jpg",
      "notes": "artifact-photo"
    },
    {
      "slug": "markerless-system",
      "title": "Markerless Motion Capture, 2020",
      "success": true,
      "chosenSource": "Wikipedia",
      "chosenUrl": "https://upload.wikimedia.org/wikipedia/commons/f/f1/Temporal-Control-and-Hand-Movement-Efficiency-in-Skilled-Music-Performance-pone.0050901.s001.ogv",
      "license": "CC BY-SA or Public Domain",
      "author": "",
      "localPath": "objects/images/markerless-system.jpg",
      "notes": "artifact-photo"
    },
    {
      "slug": "biomechanics-software",
      "title": "Biomechanics Analysis Software",
      "success": true,
      "chosenSource": "Wikipedia",
      "chosenUrl": "https://upload.wikimedia.org/wikipedia/commons/b/b5/OpenSim_GUI_1.1_By_A_Habib_2007.png",
      "license": "CC BY-SA or Public Domain",
      "author": "",
      "localPath": "objects/images/biomechanics-software.png",
      "notes": "artifact-photo"
    },
    {
      "slug": "force-plate",
      "title": "Kistler Force Plate, 2015",
      "success": true,
      "chosenSource": "Wikipedia",
      "chosenUrl": "https://upload.wikimedia.org/wikipedia/commons/1/1a/George_E._Mueller.jpg",
      "license": "CC BY-SA or Public Domain",
      "author": "",
      "localPath": "objects/images/force-plate.jpg",
      "notes": "artifact-photo"
    },
    {
      "slug": "pressure-mat",
      "title": "Pressure-Sensitive Gait Mat, 2020",
      "success": true,
      "chosenSource": "Wikipedia",
      "chosenUrl": "https://upload.wikimedia.org/wikipedia/commons/f/f3/Wii-Console.png",
      "license": "CC BY-SA or Public Domain",
      "author": "",
      "localPath": "objects/images/pressure-mat.png",
      "notes": "artifact-photo"
    },
    {
      "slug": "force-analysis-display",
      "title": "Force Analysis Visualization System",
      "success": true,
      "chosenSource": "Wikipedia",
      "chosenUrl": "https://upload.wikimedia.org/wikipedia/commons/5/54/Rayleigh-Taylor_instability.jpg",
      "license": "CC BY-SA or Public Domain",
      "author": "",
      "localPath": "objects/images/force-analysis-display.jpg",
      "notes": "artifact-photo"
    },
    {
      "slug": "biomechanics-sensor",
      "title": "IMU Sensor Array, 2018",
      "success": true,
      "chosenSource": "Wikipedia",
      "chosenUrl": "https://upload.wikimedia.org/wikipedia/commons/a/a8/VPL_DataSuit_1.jpg",
      "license": "CC BY-SA or Public Domain",
      "author": "",
      "localPath": "objects/images/biomechanics-sensor.jpg",
      "notes": "artifact-photo"
    },
    {
      "slug": "heart-rate-monitor",
      "title": "Polar Heart Rate Monitor, 1982",
      "success": true,
      "chosenSource": "Wikipedia",
      "chosenUrl": "https://upload.wikimedia.org/wikipedia/commons/5/51/Ranulph_Fiennes_2014.jpg",
      "license": "CC BY-SA or Public Domain",
      "author": "",
      "localPath": "objects/images/heart-rate-monitor.jpg",
      "notes": "artifact-photo"
    },
    {
      "slug": "smart-watch-evolution",
      "title": "Smart Watch Evolution, 2010-2020",
      "success": true,
      "chosenSource": "Wikipedia",
      "chosenUrl": "https://upload.wikimedia.org/wikipedia/commons/6/69/2023-0109-CFPtitlegame-Kirby_Smart.jpg",
      "license": "CC BY-SA or Public Domain",
      "author": "",
      "localPath": "objects/images/smart-watch-evolution.jpg",
      "notes": "artifact-photo"
    },
    {
      "slug": "gait-analyzer",
      "title": "Wearable Gait Analyzer, 2019",
      "success": true,
      "chosenSource": "The Met Museum",
      "chosenUrl": "https://images.metmuseum.org/CRDImages/is/original/DP170394.jpg",
      "license": "Public Domain",
      "author": "",
      "localPath": "objects/images/gait-analyzer.jpg",
      "notes": "artifact-photo"
    },
    {
      "slug": "performance-dashboard",
      "title": "Performance Analytics Dashboard, 2020",
      "success": true,
      "chosenSource": "Wikipedia",
      "chosenUrl": "https://upload.wikimedia.org/wikipedia/commons/8/8c/English_Wikipedia%27s_traffic_by_browser_family.png",
      "license": "CC BY-SA or Public Domain",
      "author": "",
      "localPath": "objects/images/performance-dashboard.png",
      "notes": "artifact-photo"
    },
    {
      "slug": "biomechanics-visualization",
      "title": "3D Biomechanics Visualization, 2018",
      "success": true,
      "chosenSource": "Wikipedia",
      "chosenUrl": "https://upload.wikimedia.org/wikipedia/commons/2/2b/Mechanical_components.png",
      "license": "CC BY-SA or Public Domain",
      "author": "",
      "localPath": "objects/images/biomechanics-visualization.png",
      "notes": "artifact-photo"
    },
    {
      "slug": "comparative-analysis",
      "title": "Comparative Performance Analysis System",
      "success": true,
      "chosenSource": "The Met Museum",
      "chosenUrl": "https://images.metmuseum.org/CRDImages/ep/original/DP-14882-001.jpg",
      "license": "Public Domain",
      "author": "",
      "localPath": "objects/images/comparative-analysis.jpg",
      "notes": "artifact-photo"
    },
    {
      "slug": "vr-training-pod",
      "title": "VR Training Pod, 2023",
      "success": true,
      "chosenSource": "Wikipedia",
      "chosenUrl": "https://upload.wikimedia.org/wikipedia/commons/e/ee/Reality_check_ESA384313.jpg",
      "license": "CC BY-SA or Public Domain",
      "author": "",
      "localPath": "objects/images/vr-training-pod.jpg",
      "notes": "artifact-photo"
    },
    {
      "slug": "vr-sports-sim",
      "title": "VR Sports Simulation System",
      "success": true,
      "chosenSource": "The Met Museum",
      "chosenUrl": "https://images.metmuseum.org/CRDImages/ep/original/DP143181.jpg",
      "license": "Public Domain",
      "author": "",
      "localPath": "objects/images/vr-sports-sim.jpg",
      "notes": "artifact-photo"
    },
    {
      "slug": "haptic-feedback-system",
      "title": "Haptic Feedback Training Suit",
      "success": true,
      "chosenSource": "Wikipedia",
      "chosenUrl": "https://upload.wikimedia.org/wikipedia/commons/6/6f/Chief_Master_Sgt._Mark_Umfleet%2C_317th_Airlift_Wing_command_chief%2C_tests_HaptX_Gloves_Development_Kit_2_at_Dyess_Air_Force_Base%2C_Texas%2C_May_10%2C_2021.jpg",
      "license": "CC BY-SA or Public Domain",
      "author": "",
      "localPath": "objects/images/haptic-feedback-system.jpg",
      "notes": "artifact-photo"
    },
    {
      "slug": "ai-coaching-system",
      "title": "AI Performance Coach, 2024",
      "success": true,
      "chosenSource": "The Met Museum",
      "chosenUrl": "https://images.metmuseum.org/CRDImages/ep/original/DP-687-001.jpg",
      "license": "Public Domain",
      "author": "",
      "localPath": "objects/images/ai-coaching-system.jpg",
      "notes": "artifact-photo"
    },
    {
      "slug": "neural-interface",
      "title": "Neural Interface Prototype, 2026",
      "success": true,
      "chosenSource": "Wikipedia",
      "chosenUrl": "https://upload.wikimedia.org/wikipedia/commons/b/bf/Ray-Ban_Stories.jpg",
      "license": "CC BY-SA or Public Domain",
      "author": "",
      "localPath": "objects/images/neural-interface.jpg",
      "notes": "artifact-photo"
    },
    {
      "slug": "predictive-analytics",
      "title": "Predictive Performance Analytics, 2024",
      "success": true,
      "chosenSource": "Wikipedia",
      "chosenUrl": "https://upload.wikimedia.org/wikipedia/commons/8/8c/English_Wikipedia%27s_traffic_by_browser_family.png",
      "license": "CC BY-SA or Public Domain",
      "author": "",
      "localPath": "objects/images/predictive-analytics.jpg",
      "notes": "artifact-photo"
    },
    {
      "slug": "holographic-display",
      "title": "Holographic Performance Visualization, 2025",
      "success": true,
      "chosenSource": "Wikipedia",
      "chosenUrl": "https://upload.wikimedia.org/wikipedia/commons/a/ad/Suteki_Hololens_applikation_.jpg",
      "license": "CC BY-SA or Public Domain",
      "author": "",
      "localPath": "objects/images/holographic-display.jpg",
      "notes": "artifact-photo"
    },
    {
      "slug": "future-prototype",
      "title": "Bio-Integrated Performance System, 2027",
      "success": true,
      "chosenSource": "Wikipedia",
      "chosenUrl": "https://upload.wikimedia.org/wikipedia/commons/8/8a/AutoFISH.jpg",
      "license": "CC BY-SA or Public Domain",
      "author": "",
      "localPath": "objects/images/future-prototype.jpg",
      "notes": "artifact-photo"
    },
    {
      "slug": "bio-integrated-sensors",
      "title": "Bio-Integrated Sensor Array, 2026",
      "success": true,
      "chosenSource": "Wikipedia",
      "chosenUrl": "https://upload.wikimedia.org/wikipedia/commons/4/4b/Effigy_mounds_lidar.jpg",
      "license": "CC BY-SA or Public Domain",
      "author": "",
      "localPath": "objects/images/bio-integrated-sensors.jpg",
      "notes": "artifact-photo"
    },
    {
      "slug": "carbon-plate-shoe",
      "title": "Nike Vaporfly with Carbon Plate, 2017",
      "success": true,
      "chosenSource": "Wikipedia",
      "chosenUrl": "https://upload.wikimedia.org/wikipedia/commons/0/0d/Nike_Vaporfly_Cut_in_Half.png",
      "license": "CC BY-SA or Public Domain",
      "author": "",
      "localPath": "objects/images/carbon-plate-shoe.png",
      "notes": "artifact-photo"
    },
    {
      "slug": "gps-watch",
      "title": "Garmin GPS Watch, 2003",
      "success": true,
      "chosenSource": "Wikipedia",
      "chosenUrl": "https://upload.wikimedia.org/wikipedia/commons/3/36/Forerunner_945_Music.jpg",
      "license": "CC BY-SA or Public Domain",
      "author": "",
      "localPath": "objects/images/gps-watch.jpg",
      "notes": "artifact-photo"
    },
    {
      "slug": "power-meter",
      "title": "SRM Power Meter, 1986",
      "success": true,
      "chosenSource": "Wikipedia",
      "chosenUrl": "https://upload.wikimedia.org/wikipedia/commons/a/a4/SRM_Origin_Power_Meter.jpg",
      "license": "CC BY-SA or Public Domain",
      "author": "",
      "localPath": "objects/images/power-meter.jpg",
      "notes": "artifact-photo"
    },
    {
      "slug": "altitude-tent",
      "title": "Altitude Training Tent, 1990s",
      "success": true,
      "chosenSource": "Wikipedia",
      "chosenUrl": "https://upload.wikimedia.org/wikipedia/commons/f/f0/Swiss_Olympic_training_base.jpg",
      "license": "CC BY-SA or Public Domain",
      "author": "",
      "localPath": "objects/images/altitude-tent.jpg",
      "notes": "artifact-photo"
    },
    {
      "slug": "exoskeleton-prototype",
      "title": "Performance Exoskeleton Prototype, 2025",
      "success": true,
      "chosenSource": "Wikipedia",
      "chosenUrl": "https://upload.wikimedia.org/wikipedia/commons/9/91/Biomimetics-09-00520-g001.png",
      "license": "CC BY-SA or Public Domain",
      "author": "",
      "localPath": "objects/images/exoskeleton-prototype.png",
      "notes": "artifact-photo"
    }
  ]
}